phonenumber_field/__init__.py
phonenumber_field/formfields.py
phonenumber_field/modelfields.py
phonenumber_field/phonenumber.py
phonenumber_field/serializerfields.py
phonenumber_field/validators.py
phonenumber_field/version.py
phonenumber_field/widgets.py
phonenumber_field/locale/ar/LC_MESSAGES/django.mo
phonenumber_field/locale/ar/LC_MESSAGES/django.po
phonenumber_field/locale/az/LC_MESSAGES/django.mo
phonenumber_field/locale/az/LC_MESSAGES/django.po
phonenumber_field/locale/bg/LC_MESSAGES/django.mo
phonenumber_field/locale/bg/LC_MESSAGES/django.po
phonenumber_field/locale/bn/LC_MESSAGES/django.mo
phonenumber_field/locale/bn/LC_MESSAGES/django.po
phonenumber_field/locale/cs/LC_MESSAGES/django.mo
phonenumber_field/locale/cs/LC_MESSAGES/django.po
phonenumber_field/locale/da/LC_MESSAGES/django.mo
phonenumber_field/locale/da/LC_MESSAGES/django.po
phonenumber_field/locale/de/LC_MESSAGES/django.mo
phonenumber_field/locale/de/LC_MESSAGES/django.po
phonenumber_field/locale/eo/LC_MESSAGES/django.mo
phonenumber_field/locale/eo/LC_MESSAGES/django.po
phonenumber_field/locale/es/LC_MESSAGES/django.mo
phonenumber_field/locale/es/LC_MESSAGES/django.po
phonenumber_field/locale/es_AR/LC_MESSAGES/django.mo
phonenumber_field/locale/es_AR/LC_MESSAGES/django.po
phonenumber_field/locale/fa/LC_MESSAGES/django.mo
phonenumber_field/locale/fa/LC_MESSAGES/django.po
phonenumber_field/locale/fi/LC_MESSAGES/django.mo
phonenumber_field/locale/fi/LC_MESSAGES/django.po
phonenumber_field/locale/fr/LC_MESSAGES/django.mo
phonenumber_field/locale/fr/LC_MESSAGES/django.po
phonenumber_field/locale/he/LC_MESSAGES/django.mo
phonenumber_field/locale/he/LC_MESSAGES/django.po
phonenumber_field/locale/hy/LC_MESSAGES/django.mo
phonenumber_field/locale/hy/LC_MESSAGES/django.po
phonenumber_field/locale/id/LC_MESSAGES/django.mo
phonenumber_field/locale/id/LC_MESSAGES/django.po
phonenumber_field/locale/it/LC_MESSAGES/django.mo
phonenumber_field/locale/it/LC_MESSAGES/django.po
django_phonenumber_field-8.0.0.dist-info/AUTHORS
django_phonenumber_field-8.0.0.dist-info/LICENSE
django_phonenumber_field-8.0.0.dist-info/METADATA
django_phonenumber_field-8.0.0.dist-info/WHEEL
django_phonenumber_field-8.0.0.dist-info/top_level.txt
django_phonenumber_field-8.0.0.dist-info/RECORD
