Metadata-Version: 2.1
Name: django-phonenumber-field
Version: 8.0.0
Summary: An international phone number field for django models.
Author-email: Stefan Foulis <stefan@foulis.ch>, François Freitag <mail@franek.fr>
Maintainer-email: François Freitag <mail@franek.fr>, Stefan Foulis <stefan@foulis.ch>
License: MIT
Project-URL: Homepage, https://github.com/stefanfoulis/django-phonenumber-field
Project-URL: Documentation, https://django-phonenumber-field.readthedocs.io/
Project-URL: Source, https://github.com/stefanfoulis/django-phonenumber-field
Project-URL: Tracker, https://github.com/stefanfoulis/django-phonenumber-field/issues/
Project-URL: Changelog, https://github.com/stefanfoulis/django-phonenumber-field/releases/
Classifier: Development Status :: 5 - Production/Stable
Classifier: Framework :: Django
Classifier: Framework :: Django :: 3.2
Classifier: Framework :: Django :: 4.2
Classifier: Framework :: Django :: 5.0
Classifier: Intended Audience :: Developers
Classifier: License :: OSI Approved :: MIT License
Classifier: Operating System :: OS Independent
Classifier: Programming Language :: Python
Classifier: Programming Language :: Python :: 3
Classifier: Programming Language :: Python :: 3 :: Only
Classifier: Programming Language :: Python :: 3.8
Classifier: Programming Language :: Python :: 3.9
Classifier: Programming Language :: Python :: 3.10
Classifier: Programming Language :: Python :: 3.11
Classifier: Programming Language :: Python :: 3.12
Classifier: Programming Language :: Python :: Implementation :: CPython
Classifier: Topic :: Internet :: WWW/HTTP
Requires-Python: >=3.8
License-File: LICENSE
License-File: AUTHORS
Requires-Dist: Django>=3.2
Provides-Extra: phonenumbers
Requires-Dist: phonenumbers>=7.0.2; extra == "phonenumbers"
Provides-Extra: phonenumberslite
Requires-Dist: phonenumberslite>=7.0.2; extra == "phonenumberslite"
